{
  "Template": {
    "TemplateName": "BankTransferGuide_jp",
    "SubjectPart": "【クラウディア マーケット】購入確定完了（銀行振込）（自動送信）",
    "TextPart": "＜本メールは返信できません。ご了承ください。＞\n\n{{name}} 様\n【クラウディア マーケット】をご利用いただき誠にありがとうございます。\n\nお支払い方法を銀行振込にご指定いただきましたので、下記の通りご案内いたします。\n\n────────────────────\n■ お振込先口座情報\n────────────────────\n銀行名 : 三井住友銀行\n口座名義 : 山田 太郎\n口座番号 : 436-074236\n\n────────────────────\n■ お振込み時の注意事項\n────────────────────\n- 必ずご注文者様名とご入金者様名を同一にしてください。\n  （異なる場合は自動確認ができませんので、カスタマーサポートまでご連絡ください。）\n\n- お振込期限：ご注文日を含め3日以内\n  （例：{{orderDate}} にご購入の場合 → {{dueDate}} まで）\n\n- ご入金が確認でき次第、自動的にご注文が確定され、メールにてご案内いたします。\n\n- 期限内にご入金が確認できない場合は、ご注文は自動的にキャンセルされ、関連のお知らせメールが送信されます。\n\n────────────────────\n■ 入金確認時間\n────────────────────\n平日：09:00 ～ 18:00\n土日・祝日：翌営業日以降、順次確認\n\n────────────────────\n■ お問い合わせ先\n────────────────────\nメール：play.support@cloudia-market.example\n\n今後とも【クラウディア マーケット】をよろしくお願いいたします。\nありがとうございます。\n\n————————————————————————————————————————\n送信元：クラウディア マーケット\n27F, Shinjuku Center Building, Nishi-Shinjuku, Shinjuku-ku, Tokyo 163-0627, Japan\nCopyright © 2026 Cloudia Market. All rights reserved.\n————————————————————————————————————————",
    "HtmlPart": "<html><body style=\"font-family: Arial, sans-serif; color: #000; font-size: 14px; line-height: 1.7;\">\n  <p>＜本メールは返信できません。ご了承ください。＞</p>\n\n  <p><strong>{{name}}</strong> 様<br>\n  【クラウディア マーケット】をご利用いただき誠にありがとうございます。</p>\n\n  <p>お支払い方法を<strong>銀行振込</strong>にご指定いただきましたので、下記の通りご案内いたします。</p>\n\n  <hr>\n  <h4>■ お振込先口座情報</h4>\n  <p>\n    銀行名 : 三井住友銀行<br>\n    口座名義 : 山田 太郎<br>\n    口座番号 : <strong style=\"color:#1a73e8;\">436-074236</strong>\n  </p>\n\n  <hr>\n  <h4>■ お振込み時の注意事項</h4>\n  <ul>\n    <li>必ず<strong>ご注文者様名＝ご入金者様名</strong>でお振込みください。<br>\n      （異なる場合は自動確認ができませんので、カスタマーサポートまでご連絡ください。）</li>\n    <li>お振込期限：<strong style=\"color:#d93025;\">ご注文日を含め3日以内</strong><br>\n      （例：{{orderDate}} にご購入の場合 → {{dueDate}} まで）</li>\n    <li>ご入金が確認でき次第、自動的にご注文が確定され、メールにてご案内いたします。</li>\n    <li>期限内にご入金が確認できない場合は、ご注文は自動的にキャンセルされます。</li>\n  </ul>\n\n  <hr>\n  <h4>■ 入金確認時間</h4>\n  <p>\n    平日：09:00 ～ 18:00<br>\n    土日・祝日：翌営業日以降、順次確認\n  </p>\n\n  <hr>\n  <h4>■ お問い合わせ先</h4>\n  <p>\n    メール：<a href=\"mailto:play.support@cloudia-market.example\">play.support@cloudia-market.example</a>\n  </p>\n\n  <p>今後とも<strong>【クラウディア マーケット】</strong>をよろしくお願いいたします。<br>\n  ありがとうございます。</p>\n\n  <hr>\n  <p style=\"font-size: 12px;\">\n    送信元：クラウディア マーケット<br>\n    27F, Shinjuku Center Building, Nishi-Shinjuku, Shinjuku-ku, Tokyo 163-0627, Japan<br>\n    Copyright © 2026 Cloudia Market. All rights reserved.\n  </p>\n</body></html>"
  }
}